get_title/__init__.py
get_title/get_title.py
get_title-0.1.0.dist-info/WHEEL
get_title-0.1.0.dist-info/METADATA
get_title-0.1.0.dist-info/RECORD
