Metadata-Version: 2.1
Name: get-title
Version: 0.1.0
Summary: get the title of a web page
Author: albert patterson
Author-email: apatterson189@gmail.com
Requires-Python: >=3.9,<4.0
Classifier: Programming Language :: Python :: 3
Classifier: Programming Language :: Python :: 3.10
Classifier: Programming Language :: Python :: 3.9
Requires-Dist: beautifulsoup4 (>=4.11.1,<5.0.0)
Requires-Dist: requests (>=2.28.0,<3.0.0)
